dashplus.py
dashplus-0.1.2.dist-info/WHEEL
dashplus-0.1.2.dist-info/METADATA
dashplus-0.1.2.dist-info/RECORD
